<?xml version="1.0" encoding="utf-8"?>
<odoo>
    <record id="eor_sale_paperformat" model="report.paperformat">
        <field name="name">EOR Sales Letter</field>
        <field name="default" eval="True"/>
        <field name="format">Letter</field>
        <field name="page_height">0</field>
        <field name="page_width">0</field>
        <field name="orientation">Portrait</field>
        <field name="margin_top">15</field>
        <field name="margin_bottom">20</field>
        <field name="margin_left">7</field>
        <field name="margin_right">7</field>
        <field name="header_line" eval="False"/>
        <field name="header_spacing">8</field>
        <field name="dpi">90</field>
    </record>

    <record id="sale.action_report_saleorder" model="ir.actions.report">
        <field name="paperformat_id" ref="eor_sale.eor_sale_paperformat"/>
    </record>

    <template id="sale.report_saleorder">
        <t t-call="web.html_container">
            <t t-foreach="docs" t-as="doc">
                <t t-if="doc.amount_transfer_fee > 0" t-call="eor_sale.report_saleorder_itc_document"
                   t-lang="doc.partner_id.lang"/>
                <t t-else="" t-call="eor_sale.report_saleorder_document" t-lang="doc.partner_id.lang"/>
            </t>
        </t>
    </template>
    <template id="report_saleorder_document">
        <t t-call="eor_sale.sale_external_layout">
            <t t-set="doc" t-value="doc.with_context({'lang':doc.partner_id.lang})"/>
            <div class="page" style="padding-top: 22px;font-size:14px;">
                <style>
                    .content {
                    font-family: Arial, Verdana, sans-serif !important;
                    }
                    .content *{
                    font-family: inherit !important;
                    }
                </style>
                <div class="oe_structure"/>
                <div class="content">
                    <div class="row">
                        <!--INFORMACIÓN DE EMPRESA-->
                        <div class="col-4">
                            <div>
                                <strong t-field="doc.company_id.partner_id.name"/>
                            </div>
                            <div>
                                <span t-field="doc.company_id.partner_id.street"/>
                                <span t-field="doc.company_id.partner_id.street2"/>
                            </div>
                            <div>
                                <span t-field="doc.company_id.partner_id.city"/>,
                                <span t-field="doc.company_id.partner_id.state_id"/>
                            </div>
                            <div>
                                <span t-field="doc.company_id.partner_id.country_id"/>
                                <span t-field="doc.company_id.partner_id.zip"/>
                            </div>
                            <div>
                                <span>RFC:</span>&#160;<span t-field="doc.company_id.rfc"/>
                            </div>
                            <div>
                                <span>Tels:</span>&#160;<span t-field="doc.company_id.phone"/>
                            </div>
                        </div>
                        <div class="col-4">
                            <div t-if="doc.date_order">
                                <strong t-if="doc.state in ['draft', 'sent']">Cotizado el:</strong>
                                <strong t-if="doc.state in ['sale']">Fecha de Venta:</strong>
                                <p t-field="doc.date_order"/>
                            </div>
                            <div t-if="doc.user_id.name">
                                <strong t-if="doc.state in ['draft', 'sent']">Atendió:</strong>
                                <strong t-if="doc.state in ['sale']">Vendedor:</strong>
                                <p t-field="doc.user_id"/>
                            </div>
                        </div>
                        <div class="col-6">
                            <div t-if="doc.partner_id">
                                <strong t-if="doc.state in ['draft', 'sent']">Con atención a:</strong>
                                <strong t-if="doc.state in ['sale']">Cliente:</strong>
                                <p><strong t-field="doc.partner_id.name"/></p>
                                <p t-field="doc.partner_id" t-options='{"widget": "contact", "fields": ["address"], "no_marker": True}'/>
                            </div>
                        </div>
                    </div>
                    <br/>
                    <table class="table table-sm">
                        <thead>
                            <tr class="border-black">
                                <th class="text-left">Clave</th>
                                <th class="text-left">Descripción</th>
                                <th class="text-right">Cantidad</th>
                                <th class="text-right">Unidad</th>
                                <th class="text-right">Precio Neto</th>
                                <th class="text-right">Precio x pieza</th>
                                <th class="text-right">Importe</th>
                            </tr>
                        </thead>
                        <tbody class="sale_tbody">

                            <t t-set="current_subtotal" t-value="0"/>

                            <t t-foreach="doc.order_line" t-as="line">

                                <t t-set="current_subtotal" t-value="current_subtotal + line.price_subtotal"
                                   groups="account.group_show_line_subtotals_tax_excluded"/>
                                <t t-set="current_subtotal" t-value="current_subtotal + line.price_total"
                                   groups="account.group_show_line_subtotals_tax_included"/>

                                <tr t-att-class="'bg-200 font-weight-bold' if line.display_type == 'line_section' else 'font-italic' if line.display_type == 'line_note' else ''">
                                    <t t-if="not line.display_type">
                                        <td>
                                            <span t-field="line.product_id.default_code"/>
                                        </td>
                                        <td>
                                            <span t-field="line.product_id.name"/>
                                        </td>
                                        <td class="text-right">
                                            <span t-field="line.product_uom_qty" t-options="{'widget': 'float', 'precision': 2}"/>
                                        </td>
                                        <td class="text-right">
                                            <span t-field="line.product_uom" groups="uom.group_uom"/>
                                        </td>
                                        <td class="text-right">
                                            <span t-field="line.price_unit_tax" t-options="{'widget': 'float', 'precision': 2}"/>
                                        </td>
                                        <td class="text-right">
                                            <span t-field="line.precio_x_pieza"/>
                                        </td>
                                        <td class="text-right">
                                            <span t-field="line.price_total"/>
                                        </td>
                                    </t>
                                </tr>
                            </t>
                            <tr class="is-subtotal text-right">
                                <td t-att-colspan="colspan">
                                    <strong class="mr16">Artículos:</strong>
                                    <span t-esc="len(doc.order_line)"/>
                                </td>
                                <td>
                                    <strong class="mr16">Total Unidades:</strong>
                                    <span t-esc="sum(doc.mapped('order_line.product_uom_qty'))"/>
                                </td>
                                <td></td>
                                <td></td>
                                <td colspan="3" rowspan="2">
                                    <div name="total">
                                        <table class="table table-sm">
<!--                                            <tr class="border-black" style="border-bottom:1px solid #dddddd;">-->
<!--                                                <td>-->
<!--                                                    <strong>Subtotal</strong>-->
<!--                                                </td>-->
<!--                                                <td class="text-right">-->
<!--                                                    <span t-field="doc.amount_untaxed"/>-->
<!--                                                </td>-->
<!--                                            </tr>-->
<!--                                            <t t-foreach="doc.amount_by_group" t-as="amount_by_group">-->
<!--                                                <tr style="border-bottom:1px solid #dddddd;">-->
<!--                                                    <t t-if="amount_by_group[3] == 1 and doc.amount_untaxed == amount_by_group[2]">-->
<!--                                                        <td>-->
<!--                                                            <span t-esc="amount_by_group[0]"/>-->
<!--                                                            <span>&amp;nbsp;<span>on</span>&amp;nbsp;-->
<!--                                                                <t t-esc="amount_by_group[2]"-->
<!--                                                                   t-options='{"widget": "monetary", "display_currency": doc.pricelist_id.currency_id}'/>-->
<!--                                                            </span>-->
<!--                                                        </td>-->
<!--                                                        <td class="text-right">-->
<!--                                                            <span t-esc="amount_by_group[1]"-->
<!--                                                                  t-options='{"widget": "monetary", "display_currency": doc.pricelist_id.currency_id}'/>-->
<!--                                                        </td>-->
<!--                                                    </t>-->
<!--                                                    <t t-else="">-->
<!--                                                        <td>-->
<!--                                                            <span t-esc="amount_by_group[0]"/>-->
<!--                                                        </td>-->
<!--                                                        <td class="text-right">-->
<!--                                                            <span t-esc="amount_by_group[1]"-->
<!--                                                                  t-options='{"widget": "monetary", "display_currency": doc.pricelist_id.currency_id}'/>-->
<!--                                                        </td>-->
<!--                                                    </t>-->
<!--                                                </tr>-->
<!--                                            </t>-->
                                            <tr class="border-black">
                                                <td>
                                                    <strong>Total</strong>
                                                </td>
                                                <td class="text-right">
                                                    <strong t-field="doc.amount_total"/>
                                                </td>
                                            </tr>
                                        </table>
                                    </div>
                                </td>
                            </tr>
                            <tr t-if="doc.x_obervaciones">
                                <td colspan="4" style="border-top: none !important;">
                                    <strong>Observaciones:</strong>
                                    <p t-field="doc.x_obervaciones"/>
                                </td>
                            </tr>
                        </tbody>
                    </table>
                    <p class="text-center" style="font-style: italic;" t-if="doc.note" t-field="doc.note"/>
                </div>
                <div class="oe_structure"/>
            </div>
        </t>
    </template>
    <template id="sale_external_layout">
        <!-- Multicompany -->
        <t t-if="not o and doc">
            <t t-set="o" t-value="doc"/>
        </t>
        <t t-if="o and 'company_id' in o">
            <t t-set="company" t-value="o.company_id"></t>
        </t>
        <t t-if="not o or not 'company_id' in o">
            <t t-set="company" t-value="res_company"></t>
        </t>
        <div class="header" style="width: 100%;border-bottom: 1px solid black;">
            <table width="100%">
                <tr>
                    <td>
                        <img t-if="doc.company_id.logo"
                             t-att-src="'data:image/png;base64,%s' % to_text(doc.company_id.logo)"
                             style="max-height:130px;max-width:130px;"/>
                    </td>
                    <td width="75%" style="vertical-align:bottom;line-height:180%;">
                        <span style="font-size:30px;">
                                <span t-if="doc.state in ['draft', 'sent']">Cotización #:</span>
                                <span t-if="doc.state in ['sale']">Pedido #:</span>
                                <span t-field="doc.name"/>
                        </span>
                    </td>
                    <td class="text-right" style="font-size:14px;vertical-align:bottom;">
                        <ul style="display:inline;">
                            <li style="display:inline;">
                                <span class="page"/>
                            </li>
                            <li style="display:inline;">/</li>
                            <li style="display:inline;">
                                <span class="topage"/>
                            </li>
                        </ul>
                    </td>
                </tr>
            </table>
        </div>

        <div class="article o_report_layout_standard">
            <t t-raw="0"/>
        </div>

        <div class="footer text-center">
            <br/>
            <span style="font-size:14px; font-style: italic;"><b>¡ Gracias por su preferencia, vuelva pronto !</b></span>
        </div>
    </template>
    <template id="report_saleorder_itc_document">
        <t t-call="eor_sale.itc_sale_external_layout">
            <style>
                #devolution-table{
                width:100%;
                }
                #devolution-table tr{
                height:20px;
                }
                #devolution-table .body_row td{
                border:1px solid black;
                }
                #devolution-table thead tr th{
                border:1px solid black;
                text-align:center;
                text-transform:uppercase;
                }
                .tag_total{
                text-align:right;
                }
                .square_total{
                border:1px solid black;
                }
                .group_row{
                width:100%;
                margin-top:10px;
                }
                .group_col{
                width:50%;
                text-align:center;
                }
                .line-spacing-80 td{
                line-height:120%;
                }
                .border-head th{
                border-bottom:1px solid black !important;
                border-top:1px solid black !important;
                }
                .separator-space{
                margin-top:50px;
                }
                .separator-space-20{
                margin-top:20px;
                }
                .page {
                    font-family: Arial, Verdana, sans-serif !important;
                    font-size: 12px !important;
                }
                .page *{
                    font-family: inherit !important;
                }

            </style>
            <t t-set="doc" t-value="doc.with_context({'lang':doc.partner_id.lang})"/>
            <div class="page" style="padding-top: 22px;font-size:14px;">
                <div class="oe_structure"/>
                <div class="row">
                    <!--INFORMACIÓN DE EMPRESA-->
                    <div class="col-4">
                        <div>
                            <b><span t-field="doc.company_id.partner_id.name"/></b>
                        </div>
                        <div>
                            <span t-field="doc.company_id.partner_id.street"/>
                            <span t-field="doc.company_id.partner_id.street2"/>
                        </div>
                        <div>
                            <span t-field="doc.company_id.partner_id.city"/>,
                            <span t-field="doc.company_id.partner_id.state_id"/>
                        </div>
                        <div>
                            <span t-field="doc.company_id.partner_id.country_id"/>
                            <span t-field="doc.company_id.partner_id.zip"/>
                        </div>
                        <div>
                            RFC: <span t-field="doc.company_id.rfc"/>
                        </div>
                        <div>
                            <span>Tels:</span>&#160;<span t-field="doc.company_id.phone"/>
                        </div>
                    </div>
                    <div class="col-3">
                        <div t-if="doc.date_order">
                            <strong>Fecha de venta:</strong>
                            <p t-field="doc.date_order"/>
                        </div>
                        <div t-if="doc.user_id.name">
                            <strong>Vendedor:</strong>
                            <p t-field="doc.user_id"/>
                        </div>
                    </div>
                    <!--ATENCIÓN Y DIRECCIÓN DE ENVIO-->
                    <div class="col-5">
                        <div><strong>Cliente/Sucursal:</strong></div>
                        <div><strong t-field="doc.partner_id.name"/></div>
                        <div><span t-field="doc.partner_id"
                             t-options='{"widget": "contact", "fields": ["address", "phone", "fax"], "no_marker": True, "phone_icons": False}'/>
                        </div>
                        <p t-if="doc.partner_id.rfc">
                            <span>RFC: </span>
                            <span t-field="doc.partner_id.rfc"/>
                        </p>
                    </div>
                </div>
                <table class="table table-sm line-spacing-80">
                    <thead>
                        <tr class="border-head">
                            <t t-set="colspan" t-value="5"/>
                            <th class="text-left">[Clave]Descripción</th>
                            <th class="text-right">Cantidad</th>
                            <th class="text-right">Unidad</th>
                            <th class="text-right">Precio unitario</th>
                            <th class="text-right">Impuesto</th>
                            <th class="text-right">Precio Neto</th>
                            <th class="text-right">Precio x pieza</th>
                            <th class="text-right">Sub-Total</th>
                        </tr>
                    </thead>
                    <tbody class="sale_tbody">
                        <t t-set="current_subtotal" t-value="0"/>
                        <t t-foreach="doc.order_line" t-as="line">
                            <t t-set="current_subtotal" t-value="current_subtotal + line.price_subtotal"
                               groups="account.group_show_line_subtotals_tax_excluded"/>
                            <t t-set="current_subtotal" t-value="current_subtotal + line.price_total"
                               groups="account.group_show_line_subtotals_tax_included"/>
                            <tr t-att-class="'bg-200 font-weight-bold' if line.display_type == 'line_section' else 'font-italic' if line.display_type == 'line_note' else ''">
                                <t t-if="not line.display_type">
                                    <td>
                                        <span t-field="line.name"/>
                                    </td>
                                    <td class="text-right">
                                        <span t-field="line.product_uom_qty"
                                              t-options="{'widget': 'float', 'precision': 2}"/>
                                    </td>
                                    <td class="text-right">
                                        <span t-field="line.product_uom" groups="uom.group_uom"/>
                                    </td>
                                    <td class="text-right">
                                        <span t-field="line.price_unit"
                                              t-options="{'widget': 'float', 'precision': 2}"/>
                                    </td>
                                    <td class="text-right">
                                        <span t-esc="', '.join(map(lambda x: (x.description or x.name), line.tax_id))"/>
                                    </td>
                                    <td class="text-right">
                                        <span t-field="line.price_unit_tax"
                                              t-options="{'widget': 'float', 'precision': 2}"/>
                                    </td>
                                    <td class="text-right">
                                        <span t-field="line.precio_x_pieza"/>
                                    </td>
                                    <td class="text-right">
                                        <span t-field="line.price_subtotal"/>
                                    </td>
                                </t>
                            </tr>
                        </t>
                        <tr>
                            <td>Artículos:
                                <b>
                                    <t t-esc="len(doc.order_line)"/>
                                </b>
                            </td>
                            <td colspan="3">Unidades:
                                <b>
                                    <t t-esc="'{:10.2f}'.format(sum(doc.mapped('order_line.product_uom_qty')))"/>
                                </b>
                            </td>
                            <td colspan="4" rowspan="2">
                                <div name="total">
                                    <div>
                                        <table class="table table-sm">
                                            <tr class="border-black" style="border-bottom:1px solid #dddddd;">
                                                <td>
                                                    <strong>Subtotal</strong>
                                                </td>
                                                <td class="text-right">
                                                    <span t-field="doc.amount_untaxed"/>
                                                </td>
                                            </tr>
                                            <tr style="border-bottom:1px solid #dddddd;">
                                                <td>
                                                    <span>Impuestos</span>
                                                </td>
                                                <td class="text-right">
                                                    <span t-field="doc.amount_tax"/>
                                                </td>
                                            </tr>
                                            <tr style="border-bottom:1px solid #dddddd;">
                                                <td>
                                                    <span>Cargo por Traspaso(</span>
                                                    <span t-field="doc.transfer_fee_id"/>
                                                    <span>%)</span>
                                                </td>
                                                <td class="text-right">
                                                    <span t-field="doc.amount_transfer_fee"
                                                          t-options="{'widget': 'monetary', 'display_currency': doc.company_id.currency_id}"/>
                                                </td>
                                            </tr>
                                            <tr class="border-black">
                                                <td>
                                                    <strong>Total</strong>
                                                </td>
                                                <td class="text-right">
                                                    <strong><span t-field="doc.amount_total"/></strong>
                                                </td>
                                            </tr>
                                        </table>
                                    </div>
                                </div>
                            </td>
                        </tr>
                        <tr>
                            <td colspan="4" style="border:none; line-height:140%">
                                <p>
                                    <b>Observaciones:</b>
                                    <span t-field="doc.x_obervaciones"/>
                                </p>
                            </td>
                        </tr>
                        <tr>
                            <td colspan="10" style="border:none;text-align:center;padding:5px;line-height:100%">
                                <span class="" style="font-style: italic">
                                    <t t-esc="doc.note"/>
                                </span>
                            </td>
                        </tr>
                    </tbody>
                </table>
                <div>
                    <table id="devolution-table">
                        <thead>
                            <tr>
                                <th>Clave</th>
                                <th>Devolución/Producto</th>
                                <th>Cant./unidad</th>
                                <th>Precio U.</th>
                                <th>Importe</th>
                                <th>Motivo</th>
                            </tr>
                        </thead>
                        <tbody>
                            <t t-set="dev_index" t-value="0"/>
                            <t t-foreach="doc.order_line" t-as="line">
                                <t t-if="5 > dev_index">
                                    <tr class="body_row">
                                        <td></td>
                                        <td></td>
                                        <td></td>
                                        <td></td>
                                        <td></td>
                                        <td></td>
                                    </tr>
                                    <t t-set="dev_index" t-value="dev_index + 1"/>
                                </t>
                            </t>
                        </tbody>
                        <ftoot>
                            <tr class="footer_row">
                                <td colspan="4" class="tag_total">
                                    <span><i><b>TOTAL A DESCONTAR+CARGO POR TRASPASO(%):</b></i></span>
                                </td>
                                <td class="square_total"></td>
                                <td></td>
                            </tr>
                            <tr class="footer_row">
                                <td colspan="4" class="tag_total">
                                    <span><i><b>NETO A PAGAR:</b></i></span>
                                </td>
                                <td class="square_total"></td>
                                <td></td>
                            </tr>
                        </ftoot>
                    </table>
                    <div style="page-break-before:auto">
                        <table class="group_row">
                            <tr>
                                <td class="group_col">RECEPCIÓN / DEVOLUCIÓN SUCURSAL</td>
                                <td class="group_col">REPARTIDOR ALMACÉN CENTRAL</td>
                            </tr>
                        </table>
                        <table class="separator-space-20 group_row">
                            <tr>
                                <td class="group_col">
                                    ______________________________________________
                                    <br/>
                                    NOMBRE Y FIRMA
                                </td>
                                <td class="group_col">
                                    ______________________________________________
                                    <br/>
                                    NOMBRE Y FIRMA
                                </td>
                            </tr>
                        </table>
                        <article>
                            <h6 class="text-center">RECIBÍ DE CONFORMIDAD</h6>
                            <p>Debo(emos) y por este pagaré me(nos) obligo(amos) a pagar a la vista incondicionalmente a la
                                orden de Grupo Abarrotero Guererrense, S.A. de
                                C.V. la cantidad de: <b>$_________________ (_________________________________________/100
                                    M.N.</b>) valor de la mercancía que he(mos)
                                recibido de conformidad el <b>______/_________/___________</b>.
                            </p>
                        </article>
                        <div class="text-center separator-space-20">
                            <p>______________________________________________<br/>NOMBRE Y FIRMA ENCARGADO(A)
                            </p>
                        </div>
                    </div>
                </div>
            </div>
        </t>
    </template>
    <template id="itc_sale_external_layout">
        <!-- Multicompany -->
        <t t-if="not o and doc">
            <t t-set="o" t-value="doc"/>
        </t>
        <t t-if="o and 'company_id' in o">
            <t t-set="company" t-value="o.company_id"></t>
        </t>
        <t t-if="not o or not 'company_id' in o">
            <t t-set="company" t-value="res_company"></t>
        </t>
        <div class="header" style="width: 100%;border-bottom: 1px solid black;">
            <table width="100%">
                <tbody>
                    <tr>
                        <td width="18%" style="vertical-align:bottom;">
                            <img t-if="doc.company_id.logo"
                                 t-att-src="'data:image/png;base64,%s' % to_text(doc.company_id.logo)"
                                 style="max-height:135px;max-width:135px;"/>
                        </td>
                        <td width="62%" style="vertical-align:bottom;line-height:180%">
                            <div t-if="doc.date_order" class="fa-2x">
                                <span> Pedido #:</span>
                                <span t-field="doc.name"/>
                            </div>
                        </td>
                        <td width="20%" style="text-align:right;vertical-align:bottom;line-height:180%">
                            <div class="fa-2x" t-if="doc.intercompany_transfer_id">
                                <span t-field="doc.intercompany_transfer_id"/>
                            </div>
                        </td>
                    </tr>
                </tbody>
            </table>
        </div>

        <div class="article o_report_layout_standard">
            <t t-raw="0"/>
        </div>

        <div class="footer">
            <div class="text-center" style="border-top: 1px solid black;">
                <div style="font-size: 10px; color: #000;">
                    <p>
                        <b>MOTIVO DE LA DEVOLUCIÓN:</b>
                        1. NO REALIZÓ EL PEDIDO / 2. PRODUCTO EN MAL ESTADO / 3. PRODUCTO EQUIVOCADO / 4. PRODUCTO
                        FALTANTE /
                        <br/>
                        5. PRODUCTO SOBRANTE / 6. ERROR DE SISTEMA / 7. OTRO
                        (ESPECIFICAR)___________________________________________________________________
                    </p>
                </div>

                <div class="text-muted" style="color: #000 !important;font-size:11px;">
                    <span class="page"/>
                    /
                    <span class="topage"/>
                </div>
            </div>
        </div>
    </template>
</odoo>